scriptlocator/__init__.py
scriptlocator/scriptlocator.py
scriptlocator-0.0.2.dist-info/LICENSE
scriptlocator-0.0.2.dist-info/METADATA
scriptlocator-0.0.2.dist-info/WHEEL
scriptlocator-0.0.2.dist-info/entry_points.txt
scriptlocator-0.0.2.dist-info/top_level.txt
scriptlocator-0.0.2.dist-info/RECORD
